citadel_simulator/__init__.py
citadel_simulator/main.py
citadel_simulator/settings.py
citadel_simulator/simulator.py
citadel_simulator/web_api.py
citadel_simulator/engines/__init__.py
citadel_simulator/engines/base.py
citadel_simulator/engines/opendss_engine.py
citadel_simulator/engines/pandapower_engine.py
citadel_simulator/grid_stix_integration/__init__.py
citadel_simulator/grid_stix_integration/annotator.py
citadel_simulator/grid_stix_integration/exporter.py
citadel_simulator/grid_stix_integration/telemetry.py
citadel_simulator/models/__init__.py
citadel_simulator/models/dickert_lv.py
citadel_simulator/models/factory.py
citadel_simulator/protocols/__init__.py
citadel_simulator/protocols/base.py
citadel_simulator/protocols/dnp3_outstation.py
citadel_simulator/protocols/modbus_server.py
citadel_simulator/schemas/__init__.py
citadel_simulator/schemas/commands.py
citadel_simulator/schemas/common.py
citadel_simulator/schemas/results.py
citadel_simulator/schemas/state.py
citadel_simulator/schemas/topology.py
citadel_simulator/static/app.js
citadel_simulator/static/index.html
citadel_simulator/static/style.css
citadel_simulator/timeseries/__init__.py
citadel_simulator/timeseries/load_profiles.py
citadel_simulator/timeseries/solar_profiles.py
citadel_simulator/timeseries/wind_profiles.py
citadel_simulator-1.0.6.dist-info/licenses/LICENSE
citadel_simulator-1.0.6.dist-info/METADATA
citadel_simulator-1.0.6.dist-info/WHEEL
citadel_simulator-1.0.6.dist-info/entry_points.txt
citadel_simulator-1.0.6.dist-info/top_level.txt
citadel_simulator-1.0.6.dist-info/RECORD
