Metadata-Version: 2.4
Name: citadel-simulator
Version: 1.0.6
Summary: CITADEL Critical Infrastructure Simulator
Author: CITADEL Project
License-Expression: GPL-3.0-or-later
Project-URL: Homepage, https://github.com/argonne-citadel/citadel-simulator
Project-URL: Repository, https://github.com/argonne-citadel/citadel-simulator.git
Keywords: simulator,cybersecurity,electrical-grid,critical-infrastructure
Classifier: Development Status :: 3 - Alpha
Classifier: Intended Audience :: Developers
Classifier: Intended Audience :: Science/Research
Classifier: Programming Language :: Python :: 3
Classifier: Programming Language :: Python :: 3.12
Classifier: Topic :: Security
Classifier: Topic :: Scientific/Engineering
Requires-Python: >=3.12
License-File: LICENSE
Requires-Dist: stix2~=3.0.1
Requires-Dist: grid-stix~=2.6
Requires-Dist: flask~=3.1.0
Requires-Dist: pandapower~=3.2.0
Requires-Dist: pydantic~=2.12.0
Requires-Dist: pymodbus~=3.11.0
Requires-Dist: python-dotenv~=1.2.0
Requires-Dist: structlog~=25.5.0
Requires-Dist: numba~=0.62.0
Provides-Extra: dev
Requires-Dist: bandit>=1.8; extra == "dev"
Requires-Dist: black>=25.1; extra == "dev"
Requires-Dist: mypy>=1.17; extra == "dev"
Requires-Dist: pytest>=8.4; extra == "dev"
Requires-Dist: pytest-asyncio>=1.0; extra == "dev"
Requires-Dist: pytest-cov>=6.1; extra == "dev"
Requires-Dist: pytest-mock>=3.14; extra == "dev"
Dynamic: license-file
